ghost_control/simdevice.py
ghost_control-0.1.4.data/data/ghost_control/lib/gbild32.dll
ghost_control-0.1.4.data/data/ghost_control/lib/gbild64.dll
ghost_control-0.1.4.dist-info/LICENSE
ghost_control-0.1.4.dist-info/METADATA
ghost_control-0.1.4.dist-info/WHEEL
ghost_control-0.1.4.dist-info/top_level.txt
ghost_control-0.1.4.dist-info/RECORD
